paydunya/__init__.py
paydunya/direct_payments.py
paydunya/invoice.py
paydunya/opr.py
paydunya-1.0.7.dist-info/LICENSE.txt
paydunya-1.0.7.dist-info/METADATA
paydunya-1.0.7.dist-info/WHEEL
paydunya-1.0.7.dist-info/top_level.txt
paydunya-1.0.7.dist-info/RECORD
