Metadata-Version: 2.1
Name: paydunya
Version: 1.0.7
Summary: PAYDUNYA Python client library
Home-page: https://github.com/paydunyadev/paydunya-python-master
Author: PAYDUNYA
Author-email: paydunya@paydunya.com
License: LICENSE.txt
Keywords: paydunya mobile money payments
Platform: UNKNOWN
Classifier: Development Status :: 2 - Pre-Alpha
Classifier: Intended Audience :: Developers
Classifier: Topic :: Utilities
Classifier: License :: OSI Approved :: MIT License
License-File: LICENSE.txt
